windows_mcp/__init__.py
windows_mcp/__main__.py
windows_mcp/analytics.py
windows_mcp/desktop/__init__.py
windows_mcp/desktop/config.py
windows_mcp/desktop/service.py
windows_mcp/desktop/views.py
windows_mcp/tree/__init__.py
windows_mcp/tree/cache_utils.py
windows_mcp/tree/config.py
windows_mcp/tree/service.py
windows_mcp/tree/utils.py
windows_mcp/tree/views.py
windows_mcp/uia/__init__.py
windows_mcp/uia/controls.py
windows_mcp/uia/core.py
windows_mcp/uia/enums.py
windows_mcp/uia/events.py
windows_mcp/uia/patterns.py
windows_mcp/vdm/__init__.py
windows_mcp/vdm/core.py
windows_mcp/watchdog/__init__.py
windows_mcp/watchdog/event_handlers.py
windows_mcp/watchdog/service.py
windows_mcp-0.6.0.dist-info/METADATA
windows_mcp-0.6.0.dist-info/WHEEL
windows_mcp-0.6.0.dist-info/entry_points.txt
windows_mcp-0.6.0.dist-info/licenses/LICENSE.md
windows_mcp-0.6.0.dist-info/RECORD
