Metadata-Version: 2.4
Name: windows-mcp
Version: 0.6.0
Summary: Lightweight MCP Server for interacting with Windows Operating System.
Project-URL: homepage, https://github.com/CursorTouch
Author-email: Jeomon George <jeogeoalukka@gmail.com>
License: MIT License
License-File: LICENSE.md
Keywords: ai,ai agent,desktop,mcp,windows
Requires-Python: >=3.13
Requires-Dist: click>=8.2.1
Requires-Dist: comtypes>=1.4.15
Requires-Dist: fastmcp>=2.14.2
Requires-Dist: fuzzywuzzy>=0.18.0
Requires-Dist: markdownify>=1.1.0
Requires-Dist: pillow>=11.2.1
Requires-Dist: posthog>=7.4.0
Requires-Dist: psutil>=7.0.0
Requires-Dist: pyautogui>=0.9.54
Requires-Dist: python-dotenv>=1.1.0
Requires-Dist: python-levenshtein>=0.27.1
Requires-Dist: pywin32>=311
Requires-Dist: requests>=2.32.3
Requires-Dist: tabulate>=0.9.0
Requires-Dist: uuid7>=0.1.0
